[{"id":"78619aaa.9beb6c","type":"tab","label":"Flow 1","disabled":false,"info":""},{"id":"5a0cae2e.6667d8","type":"catch","z":"78619aaa.9beb6c","name":"","scope":null,"uncaught":false,"x":190,"y":180,"wires":[[]]},{"id":"62ada54d.5be874","type":"debug","z":"78619aaa.9beb6c","name":"","active":true,"tosidebar":true,"console":false,"tostatus":false,"complete":"false","statusVal":"","statusType":"auto","x":480,"y":120,"wires":[]},{"id":"e1721809.3b933","type":"inject","z":"78619aaa.9beb6c","name":"","props":[{"p":"payload"},{"p":"topic","vt":"str"}],"repeat":"","crontab":"","once":false,"onceDelay":0.1,"topic":"","payload":"","payloadType":"date","x":630,"y":260,"wires":[[]]},{"id":"3bbfc6d0.1ee9fa","type":"status","z":"78619aaa.9beb6c","name":"","scope":null,"x":350,"y":280,"wires":[[]]},{"id":"ef9c38e8.26acb","type":"switch","z":"78619aaa.9beb6c","name":"","property":"payload","propertyType":"msg","rules":[{"t":"eq","v":"","vt":"str"}],"checkall":"true","repair":false,"outputs":1,"x":400,"y":460,"wires":[[]]},{"id":"b25f1ac8.7c1c58","type":"switch","z":"78619aaa.9beb6c","name":"","property":"payload","propertyType":"msg","rules":[{"t":"eq","v":"","vt":"str"}],"checkall":"true","repair":false,"outputs":1,"x":400,"y":580,"wires":[[]]},{"id":"5665cb19.ad1fe4","type":"function","z":"78619aaa.9beb6c","name":"","func":"\nreturn msg;","outputs":1,"noerr":0,"initialize":"","finalize":"","x":570,"y":380,"wires":[[]]},{"id":"a42a8a9a.18b078","type":"switch","z":"78619aaa.9beb6c","name":"","property":"payload","propertyType":"msg","rules":[{"t":"eq","v":"","vt":"str"}],"checkall":"true","repair":false,"outputs":1,"x":160,"y":380,"wires":[[]]},{"id":"8f289f34.35d88","type":"trigger","z":"78619aaa.9beb6c","name":"","op1":"1","op2":"0","op1type":"val","op2type":"val","duration":"250","extend":"false","units":"ms","reset":"","bytopic":"all","topic":"topic","outputs":1,"x":250,"y":680,"wires":[[]]},{"id":"6631a10a.571428","type":"range","z":"78619aaa.9beb6c","minin":"","maxin":"","minout":"","maxout":"","action":"scale","round":false,"property":"payload","name":"","x":120,"y":520,"wires":[[]]},{"id":"3f1e844.e5bfefc","type":"template","z":"78619aaa.9beb6c","name":"","field":"payload","fieldType":"msg","format":"handlebars","syntax":"mustache","template":"This is the payload: {{payload}} !","output":"str","x":190,"y":580,"wires":[[]]},{"id":"73f8117d.95fdd","type":"trigger","z":"78619aaa.9beb6c","name":"","op1":"1","op2":"0","op1type":"val","op2type":"val","duration":"250","extend":"false","units":"ms","reset":"","bytopic":"all","topic":"topic","outputs":1,"x":210,"y":760,"wires":[[]]},{"id":"c404e154.433ce","type":"link in","z":"78619aaa.9beb6c","name":"","links":[],"x":65,"y":280,"wires":[[]]},{"id":"b300af85.a9301","type":"complete","z":"78619aaa.9beb6c","name":"","scope":[],"uncaught":false,"x":240,"y":100,"wires":[[]]},{"id":"c5cf5c9b.c67cf8","type":"link in","z":"78619aaa.9beb6c","name":"","links":[],"x":145,"y":300,"wires":[[]]},{"id":"54d2b1ca.cae078","type":"status","z":"78619aaa.9beb6c","name":"","scope":null,"x":190,"y":240,"wires":[[]]},{"id":"3fec9843.01966","type":"complete","z":"78619aaa.9beb6c","name":"","scope":[],"uncaught":false,"x":140,"y":40,"wires":[[]]},{"id":"237ca21b.7bd40e","type":"function","z":"78619aaa.9beb6c","name":"","func":"\nreturn msg;","outputs":1,"noerr":0,"initialize":"","finalize":"","x":170,"y":460,"wires":[[]]},{"id":"809f9a31.f0f7f8","type":"template","z":"78619aaa.9beb6c","name":"","field":"payload","fieldType":"msg","format":"handlebars","syntax":"mustache","template":"This is the payload: {{payload}} !","output":"str","x":130,"y":640,"wires":[[]]}]